fink_science/__init__.py
fink_science/tester.py
fink_science/data/__init__.py
fink_science/data/alerts/__init__.py
fink_science/data/catalogs/3hsp.csv
fink_science/data/catalogs/CTAO_blazars_ztf_dr22.parquet
fink_science/data/catalogs/gcvs.parquet
fink_science/data/catalogs/mangrove_filtered.parquet
fink_science/data/catalogs/table-4LAC-DR3-h.fits
fink_science/data/catalogs/table-4LAC-DR3-l.fits
fink_science/data/catalogs/tns_raw.parquet
fink_science/data/catalogs/vsx.parquet
fink_science/data/models/AGN_binary.joblib
fink_science/data/models/AGN_elasticc_alerts.joblib
fink_science/data/models/KN_PC_all_bands.npy
fink_science/data/models/KN_model_1PC.pkl
fink_science/data/models/SLSN_rainbow_no_MD.joblib
fink_science/data/models/__init__.py
fink_science/data/models/components.csv
fink_science/data/models/default-model_sigmoid.obj
fink_science/data/models/default-model_sigmoid_elasticc.obj
fink_science/data/models/default-model_sigmoid_elasticc_meta.obj
fink_science/data/models/elasticc_rainbow_earlyIa_nometa.pkl
fink_science/data/models/kilonova_model.pkl
fink_science/data/models/kn_diff_pc_sets.pkl
fink_science/data/models/mixed_pcs.csv
fink_science/data/models/pca.sav
fink_science/data/models/quantized-model-GR-noZ-28341-1654269564-0.5.1.dev73+g70f85f8-LL0.836.tflite
fink_science/data/models/rf.sav
fink_science/data/models/anomaly_detection/anomaly_detection_forest_AAD.zip
fink_science/data/models/anomaly_detection/anomaly_detection_forest_AAD_anais.zip
fink_science/data/models/anomaly_detection/anomaly_detection_forest_AAD_beta.zip
fink_science/data/models/anomaly_detection/anomaly_detection_forest_AAD_emille.zip
fink_science/data/models/anomaly_detection/anomaly_detection_forest_AAD_julien.zip
fink_science/data/models/anomaly_detection/anomaly_detection_forest_AAD_maria.zip
fink_science/data/models/anomaly_detection/g_means.csv
fink_science/data/models/anomaly_detection/r_means.csv
fink_science/data/models/cats_models/cats_small_nometa_serial.keras
fink_science-7.4.0.dist-info/LICENSE
fink_science-7.4.0.dist-info/METADATA
fink_science-7.4.0.dist-info/WHEEL
fink_science-7.4.0.dist-info/top_level.txt
fink_science-7.4.0.dist-info/RECORD
