Metadata-Version: 2.1
Name: fink-science
Version: 7.4.0
Summary: User-defined science module for the Fink broker.
Home-page: https://fink-broker.readthedocs.io/en/latest/
Author: JulienPeloton
Author-email: peloton@lal.in2p3.fr
Project-URL: Documentation, https://fink-broker.readthedocs.io/en/latest/
Project-URL: Source, https://github.com/astrolabsoftware/fink-science
Classifier: Programming Language :: Python :: 3.9
Classifier: Programming Language :: Python :: 3.10
Classifier: Programming Language :: Python :: 3.11
Classifier: License :: OSI Approved :: Apache Software License
Classifier: Operating System :: Unix
Classifier: Development Status :: 4 - Beta
Classifier: Intended Audience :: Science/Research
License-File: LICENSE
